etch/__init__.py
etch/cli/__init__.py
etch/cli/cli.py
etch/compile/__init__.py
etch/data/.keep
etch/hardware/__init__.py
etch/project/__init__.py
etch/project/project.py
etch/util/__init__.py
etch/util/constants.py
etch/util/install.py
etch/util/settings.py
etch/util/util.py
boolsi_etch-0.2.0.dist-info/METADATA
boolsi_etch-0.2.0.dist-info/WHEEL
boolsi_etch-0.2.0.dist-info/entry_points.txt
boolsi_etch-0.2.0.dist-info/licenses/LICENSE
boolsi_etch-0.2.0.dist-info/RECORD
